nb_cli_plugin_docker/__init__.py
nb_cli_plugin_docker/cli.py
nb_cli_plugin_docker/exception.py
nb_cli_plugin_docker/handler.py
nb_cli_plugin_docker/plugin.py
nb_cli_plugin_docker/static/common/.dockerignore
nb_cli_plugin_docker/static/reverse/docker/_main.py
nb_cli_plugin_docker/static/reverse/docker/gunicorn_conf.py
nb_cli_plugin_docker/static/reverse/docker/start.sh
nb_cli_plugin_docker/template/docker/_helpers.Dockerfile.jinja
nb_cli_plugin_docker/template/docker/docker-compose.yml.jinja
nb_cli_plugin_docker/template/docker/forward.Dockerfile.jinja
nb_cli_plugin_docker/template/docker/get_driver_type.py.jinja
nb_cli_plugin_docker/template/docker/reverse.Dockerfile.jinja
nb_cli_plugin_docker/utils.py
nb_cli_plugin_docker-0.5.0.dist-info/METADATA
nb_cli_plugin_docker-0.5.0.dist-info/WHEEL
nb_cli_plugin_docker-0.5.0.dist-info/entry_points.txt
nb_cli_plugin_docker-0.5.0.dist-info/licenses/LICENSE
nb_cli_plugin_docker-0.5.0.dist-info/RECORD
