Metadata-Version: 2.4
Name: nb-cli-plugin-docker
Version: 0.5.0
Summary: docker support for nb-cli
License: MIT
License-File: LICENSE
Keywords: nonebot,cli,docker
Author: yanyongyu
Author-email: yyy@nonebot.dev
Requires-Python: >=3.9,<4.0
Classifier: Development Status :: 5 - Production/Stable
Classifier: Framework :: Robot Framework
Classifier: Framework :: Robot Framework :: Library
Classifier: License :: OSI Approved :: MIT License
Classifier: Operating System :: OS Independent
Classifier: Programming Language :: Python :: 3
Classifier: Programming Language :: Python :: 3.9
Classifier: Programming Language :: Python :: 3.10
Classifier: Programming Language :: Python :: 3.11
Classifier: Programming Language :: Python :: 3.12
Classifier: Programming Language :: Python :: 3.13
Classifier: Programming Language :: Python :: 3.14
Requires-Dist: nb-cli (>=1.5.0,<2.0.0)
Requires-Dist: noneprompt (>=0.1.7,<0.2.0)
Project-URL: Documentation, https://github.com/nonebot/cli-plugin-docker#readme
Project-URL: Homepage, https://github.com/nonebot/cli-plugin-docker
Project-URL: Repository, https://github.com/nonebot/cli-plugin-docker
